{"nodes": [{"id": "formcreator_form_editor_screen", "label": "Form Editor Screen (HR Admin)", "file_type": "document", "source_file": "designs/rh/formcreator.html", "source_location": null, "source_url": null, "captured_at": null, "author": null, "contributor": null}, {"id": "formcreator_sidebar_nav", "label": "HR Sidebar Navigation (Dashboard, Team Hub, Talent Journey, Performance, Insights, Settings)", "file_type": "document", "source_file": "designs/rh/formcreator.html", "source_location": null, "source_url": null, "captured_at": null, "author": null, "contributor": null}, {"id": "formcreator_question_card", "label": "Draggable Question Card (drag_indicator, copy, delete)", "file_type": "document", "source_file": "designs/rh/formcreator.html", "source_location": null, "source_url": null, "captured_at": null, "author": null, "contributor": null}, {"id": "formcreator_properties_panel", "label": "Component Configuration / Properties Panel (right column)", "file_type": "document", "source_file": "designs/rh/formcreator.html", "source_location": null, "source_url": null, "captured_at": null, "author": null, "contributor": null}, {"id": "formcreator_validation_logic", "label": "Validation Logic Toggles (Required, Weightage Multiplier, Anonymous)", "file_type": "document", "source_file": "designs/rh/formcreator.html", "source_location": null, "source_url": null, "captured_at": null, "author": null, "contributor": null}, {"id": "formcreator_interface_options", "label": "Interface Options Grid (Scale, Dropdown, Text Area, Multiple Choice)", "file_type": "document", "source_file": "designs/rh/formcreator.html", "source_location": null, "source_url": null, "captured_at": null, "author": null, "contributor": null}], "edges": [{"source": "formcreator_form_editor_screen", "target": "formeditor_DESIGN_creator_view", "relation": "references", "confidence": "EXTRACTED", "confidence_score": 1.0, "source_file": "designs/rh/formcreator.html", "source_location": null, "weight": 1.0}, {"source": "formcreator_question_card", "target": "formeditor_DESIGN_qcard", "relation": "semantically_similar_to", "confidence": "EXTRACTED", "confidence_score": 1.0, "source_file": "designs/rh/formcreator.html", "source_location": null, "weight": 1.0}, {"source": "formcreator_properties_panel", "target": "formeditor_DESIGN_config_panel", "relation": "semantically_similar_to", "confidence": "EXTRACTED", "confidence_score": 1.0, "source_file": "designs/rh/formcreator.html", "source_location": null, "weight": 1.0}, {"source": "formcreator_interface_options", "target": "formeditor_DESIGN_field_types", "relation": "semantically_similar_to", "confidence": "INFERRED", "confidence_score": 0.85, "source_file": "designs/rh/formcreator.html", "source_location": null, "weight": 0.85}, {"source": "formcreator_validation_logic", "target": "formeditor_DESIGN_config_panel", "relation": "references", "confidence": "INFERRED", "confidence_score": 0.8, "source_file": "designs/rh/formcreator.html", "source_location": null, "weight": 0.8}, {"source": "formcreator_form_editor_screen", "target": "dashboard_DESIGN_sovereign_workspace", "relation": "conceptually_related_to", "confidence": "INFERRED", "confidence_score": 0.8, "source_file": "designs/rh/formcreator.html", "source_location": null, "weight": 0.8}], "hyperedges": []}