{"nodes": [{"id": "03screensmd_ScreensSpec", "label": "Screens Inventory 41 Screens", "file_type": "document", "source_file": "frontend-v2/specs/03-screens.md", "source_location": null, "source_url": null, "captured_at": null, "author": null, "contributor": null}, {"id": "screen_S01", "label": "Screen S-01: Login /login", "file_type": "concept", "source_file": "frontend-v2/specs/03-screens.md", "source_location": null, "source_url": null, "captured_at": null, "author": null, "contributor": null}, {"id": "screen_S02", "label": "Screen S-02: LDAP Login", "file_type": "concept", "source_file": "frontend-v2/specs/03-screens.md", "source_location": null, "source_url": null, "captured_at": null, "author": null, "contributor": null}, {"id": "screen_S03", "label": "Screen S-03: Dashboard 5 Role Variants", "file_type": "concept", "source_file": "frontend-v2/specs/03-screens.md", "source_location": null, "source_url": null, "captured_at": null, "author": null, "contributor": null}, {"id": "screen_S16", "label": "Screen S-16: Evaluations List", "file_type": "concept", "source_file": "frontend-v2/specs/03-screens.md", "source_location": null, "source_url": null, "captured_at": null, "author": null, "contributor": null}, {"id": "screen_S17", "label": "Screen S-17: Evaluation Detail", "file_type": "concept", "source_file": "frontend-v2/specs/03-screens.md", "source_location": null, "source_url": null, "captured_at": null, "author": null, "contributor": null}], "edges": [{"source": "03screensmd_ScreensSpec", "target": "screen_S01", "relation": "references", "confidence": "EXTRACTED", "confidence_score": 1.0, "source_file": "frontend-v2/specs/03-screens.md", "source_location": null, "weight": 1.0}, {"source": "03screensmd_ScreensSpec", "target": "screen_S02", "relation": "references", "confidence": "EXTRACTED", "confidence_score": 1.0, "source_file": "frontend-v2/specs/03-screens.md", "source_location": null, "weight": 1.0}, {"source": "03screensmd_ScreensSpec", "target": "screen_S03", "relation": "references", "confidence": "EXTRACTED", "confidence_score": 1.0, "source_file": "frontend-v2/specs/03-screens.md", "source_location": null, "weight": 1.0}, {"source": "03screensmd_ScreensSpec", "target": "screen_S16", "relation": "references", "confidence": "EXTRACTED", "confidence_score": 1.0, "source_file": "frontend-v2/specs/03-screens.md", "source_location": null, "weight": 1.0}, {"source": "03screensmd_ScreensSpec", "target": "screen_S17", "relation": "references", "confidence": "EXTRACTED", "confidence_score": 1.0, "source_file": "frontend-v2/specs/03-screens.md", "source_location": null, "weight": 1.0}, {"source": "screen_S01", "target": "flow_Login", "relation": "conceptually_related_to", "confidence": "INFERRED", "confidence_score": 0.9, "source_file": "frontend-v2/specs/03-screens.md", "source_location": null, "weight": 0.9}, {"source": "screen_S01", "target": "api_Auth", "relation": "references", "confidence": "INFERRED", "confidence_score": 0.9, "source_file": "frontend-v2/specs/03-screens.md", "source_location": null, "weight": 0.9}, {"source": "screen_S17", "target": "component_EvaluationForm", "relation": "references", "confidence": "EXTRACTED", "confidence_score": 1.0, "source_file": "frontend-v2/specs/03-screens.md", "source_location": null, "weight": 1.0}, {"source": "screen_S17", "target": "component_SignaturePanel", "relation": "references", "confidence": "EXTRACTED", "confidence_score": 1.0, "source_file": "frontend-v2/specs/03-screens.md", "source_location": null, "weight": 1.0}, {"source": "screen_S17", "target": "api_Evaluations", "relation": "references", "confidence": "INFERRED", "confidence_score": 0.9, "source_file": "frontend-v2/specs/03-screens.md", "source_location": null, "weight": 0.9}, {"source": "screen_S16", "target": "api_Evaluations", "relation": "references", "confidence": "INFERRED", "confidence_score": 0.9, "source_file": "frontend-v2/specs/03-screens.md", "source_location": null, "weight": 0.9}, {"source": "screen_S16", "target": "component_DataTable", "relation": "references", "confidence": "INFERRED", "confidence_score": 0.85, "source_file": "frontend-v2/specs/03-screens.md", "source_location": null, "weight": 0.85}, {"source": "screen_S03", "target": "component_Navbar", "relation": "references", "confidence": "INFERRED", "confidence_score": 0.9, "source_file": "frontend-v2/specs/03-screens.md", "source_location": null, "weight": 0.9}], "hyperedges": []}